mavis/__info__.py
mavis/__init__.py
mavis/api.py
mavis/config.py
mavis/core.py
mavis/plot.py
mavis/transfer.py
mavis/model/__init__.py
mavis/model/api.py
mavis/model/demo.py
mavis/model/iforest.py
mavis/model/boiler/__init__.py
mavis/model/boiler/config.py
mavis/model/boiler/data_read.py
mavis/model/boiler/deep_learning.py
mavis/model/boiler/draw.py
mavis/model/boiler/net.py
mix_mavis-1.0.0.dist-info/LICENSE.txt
mix_mavis-1.0.0.dist-info/METADATA
mix_mavis-1.0.0.dist-info/WHEEL
mix_mavis-1.0.0.dist-info/top_level.txt
mix_mavis-1.0.0.dist-info/RECORD
