Metadata-Version: 2.1
Name: mix-mavis
Version: 1.0.0
Summary: MAVIS 数据分析工具
Home-page: https://github.com/mixlinker/mavis
Author: mixlinker
Author-email: datascience@mixlinker.com
License: UNKNOWN
Keywords: visualization,analysis,jupyter
Platform: UNKNOWN
Classifier: Development Status :: 3 - Alpha
Classifier: Intended Audience :: Developers
Classifier: Topic :: Software Development :: Build Tools
Classifier: License :: OSI Approved :: MIT License
Classifier: Programming Language :: Python :: 3
Classifier: Programming Language :: Python :: 3.5
Classifier: Programming Language :: Python :: 3.6
Classifier: Programming Language :: Python :: 3.7
Requires-Python: >=3.5
Requires-Dist: IPython
Requires-Dist: matplotlib
Requires-Dist: seaborn
Requires-Dist: ipywidgets
Requires-Dist: numpy
Requires-Dist: pandas
Requires-Dist: scipy
Requires-Dist: scikit-learn
Requires-Dist: torch
Requires-Dist: torchvision
Requires-Dist: boto3
